{
  "header": {
    "id": "7e7b9ad6-0825-4bcf-9cd1-b56434d32dde",
    "name": "so-kt-geocat-harvester",
    "title": "SO-Kt - Geocat Harvester",
    "context": "piveau",
    "transport": "payload",
    "version": "1.0.0"
  },
  "body": {
    "segments": [
      {
        "header": {
          "name": "piveau-consus-importing-csw",
          "segmentNumber": 1,
          "title": "Importing CSW",
          "processed": false
        },
        "body": {
          "config": {
            "address": "https://www.geocat.ch/geonetwork/SO/ger/csw?SERVICE=CSW&REQUEST=GetCapabilities",
            "catalogue": "so-kt",
            "preProcessing": true,
            "org_name": ""
          }
        }
      },
      {
        "header": {
          "name": "piveau-consus-filter",
          "segmentNumber": 2,
          "title": "Filtering",
          "processed": false
        },
        "body": {
          "config": {
            "org_id": "kanton_solothurn",
            "catalogue": "so-kt",
            "preProcessing": true
          }
        }
      },
      {
        "header": {
          "name": "piveau-consus-exporting-hub",
          "segmentNumber": 3,
          "title": "Exporting hub",
          "processed": false
        },
        "body": {}
      }
    ]
  }
}